<?xml version="1.0" encoding="utf-8"?>
<labels xmlns="http://mulan.sourceforge.net/labels">
<label name="Brown-Creeper"></label>
<label name="Pacific-Wren"></label>
<label name="Pacific-slope-Flycatcher"></label>
<label name="Red-breasted-Nuthatch"></label>
<label name="Dark-eyed-Junco"></label>
<label name="Olive-sided-Flycatcher"></label>
<label name="Hermit-Thrush"></label>
<label name="Chestnut-backed-Chickadee"></label>
<label name="Varied-Thrush"></label>
<label name="Hermit-Warbler"></label>
<label name="Swainsons-Thrush"></label>
<label name="Hammonds-Flycatcher"></label>
<label name="Western-Tanager"></label>
<label name="Black-headed-Grosbeak"></label>
<label name="Golden-Crowned-Kinglet"></label>
<label name="Warbling-Vireo"></label>
<label name="MacGillivrays-Warbler"></label>
<label name="Stellars-Jay"></label>
<label name="Common-Nighthawk"></label>
</labels>